haiway/__init__.py
haiway/attributes/__init__.py
haiway/attributes/annotations.py
haiway/attributes/attribute.py
haiway/attributes/coding.py
haiway/attributes/function.py
haiway/attributes/path.py
haiway/attributes/requirement.py
haiway/attributes/specification.py
haiway/attributes/state.py
haiway/attributes/validation.py
haiway/context/__init__.py
haiway/context/access.py
haiway/context/disposables.py
haiway/context/events.py
haiway/context/identifier.py
haiway/context/observability.py
haiway/context/presets.py
haiway/context/scope.py
haiway/context/state.py
haiway/context/tasks.py
haiway/context/types.py
haiway/helpers/__init__.py
haiway/helpers/asynchrony.py
haiway/helpers/caching.py
haiway/helpers/concurrent.py
haiway/helpers/configuration.py
haiway/helpers/files.py
haiway/helpers/http_client.py
haiway/helpers/message_queue.py
haiway/helpers/observability.py
haiway/helpers/retries.py
haiway/helpers/statemethods.py
haiway/helpers/throttling.py
haiway/helpers/timeouting.py
haiway/httpx/__init__.py
haiway/httpx/client.py
haiway/opentelemetry/__init__.py
haiway/opentelemetry/observability.py
haiway/postgres/__init__.py
haiway/postgres/client.py
haiway/postgres/config.py
haiway/postgres/configuration.py
haiway/postgres/state.py
haiway/postgres/types.py
haiway/py.typed
haiway/rabbitmq/__init__.py
haiway/rabbitmq/client.py
haiway/rabbitmq/config.py
haiway/rabbitmq/connection.py
haiway/rabbitmq/state.py
haiway/rabbitmq/types.py
haiway/types/__init__.py
haiway/types/alias.py
haiway/types/basic.py
haiway/types/default.py
haiway/types/description.py
haiway/types/immutable.py
haiway/types/map.py
haiway/types/meta.py
haiway/types/missing.py
haiway/types/specification.py
haiway/utils/__init__.py
haiway/utils/collections.py
haiway/utils/env.py
haiway/utils/formatting.py
haiway/utils/logs.py
haiway/utils/queue.py
haiway/utils/stream.py
haiway-0.43.1.dist-info/WHEEL
haiway-0.43.1.dist-info/METADATA
haiway-0.43.1.dist-info/RECORD
