Metadata-Version: 2.3
Name: haiway
Version: 0.43.1
Summary: Framework for dependency injection and state management within structured concurrency model.
License: MIT License
Classifier: License :: OSI Approved :: MIT License
Classifier: Intended Audience :: Developers
Classifier: Programming Language :: Python
Classifier: Programming Language :: Python :: 3
Classifier: Programming Language :: Python :: 3 :: Only
Classifier: Programming Language :: Python :: 3.13
Classifier: Typing :: Typed
Classifier: Topic :: Software Development
Classifier: Topic :: Software Development :: Libraries :: Application Frameworks
Requires-Dist: typing-extensions~=4.15
Requires-Dist: bandit~=1.9 ; extra == 'dev'
Requires-Dist: pyright~=1.1 ; extra == 'dev'
Requires-Dist: pytest~=8.4 ; extra == 'dev'
Requires-Dist: pytest-asyncio~=1.2 ; extra == 'dev'
Requires-Dist: pytest-cov~=7.0 ; extra == 'dev'
Requires-Dist: ruff~=0.14 ; extra == 'dev'
Requires-Dist: mkdocs~=1.6 ; extra == 'docs'
Requires-Dist: mkdocs-material~=9.6 ; extra == 'docs'
Requires-Dist: mkdocstrings[python]~=0.30 ; extra == 'docs'
Requires-Dist: mdformat~=0.7 ; extra == 'docs'
Requires-Dist: mdformat-gfm~=0.4 ; extra == 'docs'
Requires-Dist: pymarkdownlnt~=0.9 ; extra == 'docs'
Requires-Dist: httpx~=0.28 ; extra == 'httpx'
Requires-Dist: opentelemetry-api~=1.37 ; extra == 'opentelemetry'
Requires-Dist: opentelemetry-sdk~=1.37 ; extra == 'opentelemetry'
Requires-Dist: opentelemetry-exporter-otlp-proto-grpc~=1.37 ; extra == 'opentelemetry'
Requires-Dist: asyncpg~=0.31.0 ; extra == 'postgres'
Requires-Dist: pika~=1.3 ; extra == 'rabbitmq'
Maintainer: Kacper Kaliński
Maintainer-email: Kacper Kaliński <kacper.kalinski@miquido.com>
Requires-Python: >=3.13
Project-URL: Homepage, https://miquido.com
Project-URL: Repository, https://github.com/miquido/haiway.git
Provides-Extra: dev
Provides-Extra: docs
Provides-Extra: httpx
Provides-Extra: opentelemetry
Provides-Extra: postgres
Provides-Extra: rabbitmq
